odoo/addons/ssi_accountant_stakeholder_report/README.rst
odoo/addons/ssi_accountant_stakeholder_report/__init__.py
odoo/addons/ssi_accountant_stakeholder_report/__manifest__.py
odoo/addons/ssi_accountant_stakeholder_report/menu.xml
odoo/addons/ssi_accountant_stakeholder_report/data/approval_template_data.xml
odoo/addons/ssi_accountant_stakeholder_report/data/ir_sequence_data.xml
odoo/addons/ssi_accountant_stakeholder_report/data/policy_template_data.xml
odoo/addons/ssi_accountant_stakeholder_report/data/sequence_template_data.xml
odoo/addons/ssi_accountant_stakeholder_report/models/__init__.py
odoo/addons/ssi_accountant_stakeholder_report/models/accountant_report.py
odoo/addons/ssi_accountant_stakeholder_report/models/accountant_stakeholder_report.py
odoo/addons/ssi_accountant_stakeholder_report/models/accountant_stakeholder_report_type.py
odoo/addons/ssi_accountant_stakeholder_report/security/ir.model.access.csv
odoo/addons/ssi_accountant_stakeholder_report/security/ir_module_category_data.xml
odoo/addons/ssi_accountant_stakeholder_report/security/ir_rule_data.xml
odoo/addons/ssi_accountant_stakeholder_report/security/res_group_data.xml
odoo/addons/ssi_accountant_stakeholder_report/static/description/icon.png
odoo/addons/ssi_accountant_stakeholder_report/views/accountant_stakeholder_report_type_views.xml
odoo/addons/ssi_accountant_stakeholder_report/views/accountant_stakeholder_report_views.xml
odoo14_addon_ssi_accountant_stakeholder_report-14.0.1.0.1.dev1.dist-info/METADATA
odoo14_addon_ssi_accountant_stakeholder_report-14.0.1.0.1.dev1.dist-info/WHEEL
odoo14_addon_ssi_accountant_stakeholder_report-14.0.1.0.1.dev1.dist-info/top_level.txt
odoo14_addon_ssi_accountant_stakeholder_report-14.0.1.0.1.dev1.dist-info/RECORD
